paddle_msssim/__init__.py
paddle_msssim/ssim.py
paddle_msssim-0.0.2.dist-info/LICENSE
paddle_msssim-0.0.2.dist-info/METADATA
paddle_msssim-0.0.2.dist-info/WHEEL
paddle_msssim-0.0.2.dist-info/top_level.txt
paddle_msssim-0.0.2.dist-info/RECORD
