Metadata-Version: 2.1
Name: paddle-msssim
Version: 0.0.2
Summary: Fast and differentiable MS-SSIM and SSIM for paddle.
Home-page: https://github.com/AgentMaker/Paddle-MSSSIM
Author: jm12138
License: UNKNOWN
Platform: UNKNOWN
Classifier: Programming Language :: Python :: 3
Classifier: License :: OSI Approved :: MIT License
Classifier: Operating System :: OS Independent
License-File: LICENSE
